hostinger_api/__init__.py
hostinger_api/api_client.py
hostinger_api/api_response.py
hostinger_api/configuration.py
hostinger_api/exceptions.py
hostinger_api/py.typed
hostinger_api/rest.py
hostinger_api/api/__init__.py
hostinger_api/api/billing_catalog_api.py
hostinger_api/api/billing_orders_api.py
hostinger_api/api/billing_payment_methods_api.py
hostinger_api/api/billing_subscriptions_api.py
hostinger_api/api/domains_portfolio_api.py
hostinger_api/api/vps_actions_api.py
hostinger_api/api/vps_backups_api.py
hostinger_api/api/vps_data_centers_api.py
hostinger_api/api/vps_firewall_api.py
hostinger_api/api/vps_malware_scanner_api.py
hostinger_api/api/vps_post_install_scripts_api.py
hostinger_api/api/vps_public_keys_api.py
hostinger_api/api/vps_recovery_api.py
hostinger_api/api/vps_snapshots_api.py
hostinger_api/api/vps_virtual_machine_api.py
hostinger_api/api/vpsos_templates_api.py
hostinger_api/api/vpsptr_records_api.py
hostinger_api/models/__init__.py
hostinger_api/models/billing_v1_catalog_catalog_item_price_resource.py
hostinger_api/models/billing_v1_catalog_catalog_item_resource.py
hostinger_api/models/billing_v1_order_order_billing_address_resource.py
hostinger_api/models/billing_v1_order_order_resource.py
hostinger_api/models/billing_v1_order_store_request.py
hostinger_api/models/billing_v1_order_store_request_items_inner.py
hostinger_api/models/billing_v1_payment_method_payment_method_resource.py
hostinger_api/models/billing_v1_subscription_cancel_request.py
hostinger_api/models/billing_v1_subscription_subscription_resource.py
hostinger_api/models/common_schema_error_response_schema.py
hostinger_api/models/common_schema_pagination_meta_schema.py
hostinger_api/models/common_schema_unauthorized_response_schema.py
hostinger_api/models/common_schema_unprocessable_content_response_schema.py
hostinger_api/models/common_schema_unprocessable_content_response_schema_errors.py
hostinger_api/models/common_success_empty_resource.py
hostinger_api-1.0.2.dist-info/METADATA
hostinger_api-1.0.2.dist-info/WHEEL
hostinger_api-1.0.2.dist-info/top_level.txt
hostinger_api-1.0.2.dist-info/RECORD
