Metadata-Version: 2.4
Name: hostinger_api
Version: 1.0.2
Summary: Hostinger API
Home-page: https://github.com/hostinger/api-python-sdk
Author: Hostinger
Author-email: devs@hostinger.com
License: MIT
Keywords: hostinger,openapi,python,sdk,rest,api
Requires-Dist: urllib3<3.0.0,>=1.25.3
Requires-Dist: python-dateutil>=2.8.2
Requires-Dist: pydantic>=2
Requires-Dist: typing-extensions>=4.7.1
Dynamic: author
Dynamic: author-email
Dynamic: description
Dynamic: description-content-type
Dynamic: home-page
Dynamic: keywords
Dynamic: license
Dynamic: requires-dist
Dynamic: summary
